kwnsgui_lib/__init__.py
kwnsgui_lib/mygui.py
kwnsgui_lib/mygui.pyi
kwnsgui_lib-0.1.0.dist-info/licenses/LICENSE
kwnsgui_lib-0.1.0.dist-info/METADATA
kwnsgui_lib-0.1.0.dist-info/WHEEL
kwnsgui_lib-0.1.0.dist-info/top_level.txt
kwnsgui_lib-0.1.0.dist-info/RECORD
