Metadata-Version: 2.4
Name: kwnsgui_lib
Version: 0.1.0
Summary: Native Windows GUI library with animation support.
Author-email: Kian William Nørgaard Sørensen <kianersej12345@gmail.com>
License: MIT
Project-URL: Homepage, https://github.com/kian140908/kwnsgui_lib
Keywords: windows,gui,animation,widgets
Classifier: Programming Language :: Python :: 3
Classifier: Operating System :: Microsoft :: Windows
Classifier: Topic :: Software Development :: Libraries
Classifier: License :: OSI Approved :: MIT License
Requires-Python: >=3.9
License-File: LICENSE
Dynamic: license-file
